stochaskit/__init__.py
stochaskit-0.0.0.dist-info/METADATA
stochaskit-0.0.0.dist-info/WHEEL
stochaskit-0.0.0.dist-info/top_level.txt
stochaskit-0.0.0.dist-info/RECORD
