Metadata-Version: 2.1
Name: stochaskit
Version: 0.0.0
Summary: Coming soon
Author-email: Normal Computing <info@normalcomputing.ai>
